<?xml version='1.0' encoding='utf-8' standalone='yes' ?>
<map>
    <string name="GsaPrefs.Bisto__whitelisted_usb_devices">18d1-5033,30a5-201</string>
    <boolean name="flag.10219" value="true" />
    <boolean name="flag.7249" value="true" />
    <boolean name="flag.10459" value="true" />
    <boolean name="flag.11787" value="true" />
    <boolean name="flag.12635" value="true" />
    <boolean name="flag.3208" value="true" />
    <boolean name="flag.10579" value="true" />
    <boolean name="flag.11786" value="true" />
    <boolean name="flag.12630" value="true" />
    <boolean name="flag.11421" value="true" />
    <boolean name="flag.12193" value="true" />
    <string name="GsaPrefs.Bisto__viable_hotword_models">Model_1.data,Model_2.data,Model_3.data,Model_4.data</string>
    <boolean name="flag.8104" value="true" />
    <boolean name="flag.8587" value="true" />
    <boolean name="flag.8103" value="true" />
    <boolean name="flag.9671" value="true" />
    <boolean name="flag.9670" value="true" />
    <boolean name="flag.8100" value="true" />
    <boolean name="flag.9430" value="true" />
    <long name="GsaPrefs.Bisto__hfp_delay" value="500" />
    <boolean name="GSAPrefs.afw_enabled" value="true" />
    <long name="flag.10900" value="60" />
    <long name="GsaPrefs.AgsaOpaGrowth__required_app_launch_count_to_show_nudge_ui" value="3" />
    <string name="GsaPrefs.AgsaOpaGrowth__approved_apps_for_nudge_ui_display"></string>
    <boolean name="flag.11678" value="true" />
    <boolean name="flag.11434" value="true" />
    <boolean name="flag.10223" value="true" />
    <long name="flag.11432" value="504" />
    <boolean name="flag.10581" value="true" />
    <long name="flag.11550" value="2000" />
    <string name="flag.11790">com.netflix.mediaclient/.ui.launch.UIWebViewActivity,com.amazon.avod.thirdpartyclient/.LauncherActivity,com.imdb.mobile/.HomeActivity,com.facebook.katana/.LoginActivity,com.instagram.android/.activity.MainTabActivity,com.snapchat.android/.LandingPageActivity,com.zhiliaoapp.musically/com.ss.android.ugc.aweme.splash.SplashActivity,com.fitbit.FitbitMobile/com.fitbit.FirstActivity,com.google.android.gm/.ConversationListActivityGmail,com.facebook.orca/.auth.StartScreenActivity,com.whatsapp/.Main,com.yahoo.mobile.client.android.mail/.activity.MainActivity,com.nianticlabs.pokemongo/com.nianticproject.holoholo.libholoholo.unity.UnityMainActivity,com.king.candycrushsaga/.CandyCrushSagaActivity,com.supercell.clashofclans/com.supercell.titan.GameApp,com.android.chrome/com.google.android.apps.chrome.Main,com.google.android.youtube/.app.honeycomb.Shell$HomeActivity,com.google.android.apps.photos/.home.HomeActivity,com.google.android.apps.maps/com.google.android.maps.MapsActivity</string>
    <boolean name="flag.10582" value="true" />
    <boolean name="flag.8575" value="true" />
    <boolean name="flag.9649" value="true" />
    <boolean name="flag.10438" value="true" />
    <long name="flag.9887" value="5" />
    <boolean name="flag.8435" value="true" />
    <boolean name="flag.9645" value="true" />
    <boolean name="flag.12616" value="true" />
    <boolean name="flag.9526" value="true" />
    <boolean name="GsaPrefs.AgsaOpa__enable_message_style_parser_for_whatsapp" value="true" />
    <boolean name="flag.4758" value="true" />
    <boolean name="flag.11642" value="true" />
    <boolean name="flag.10796" value="true" />
    <boolean name="flag.12730" value="true" />
    <string name="GsaPrefs.Bisto__dsp_hotword_model_map">cmn-hans-cn/*/CAPE,0000;cmn-hant-tw/*/CAPE,0001;cs-cz/*/CAPE,0002;en-*/*/CAPE,000D;fa-ir/*/CAPE,0004;fi-fi/*/CAPE,0005;hr-hr/*/CAPE,0007;ro-ro/*/CAPE,0008;ar-sa/*/CAPE,0009;mr-in/*/CAPE,0009;ta-in/*/CAPE,0009;te-in/*/CAPE,0009;bn-in/*/CAPE,0009;ml-in/*/CAPE,0009;ur-in/*/CAPE,0009;gu-in/*/CAPE,0009;kn-in/*/CAPE,0009;pa-in/*/CAPE,0009;da-dk/*/CAPE,000B;de-*/*/CAPE,000C;es-*/*/CAPE,000E;fr-*/*/CAPE,000F;hi-in/*/CAPE,000G;it-it/*/CAPE,000H;ja-jp/*/CAPE,000I;ko-kr/*/CAPE,000J;nb-no/*/CAPE,000K;nl-nl/*/CAPE,000L;pt-br/*/CAPE,000M;ru-ru/*/CAPE,000N;sv-se/*/CAPE,000O;id-id/*/CAPE,000P;th-th/*/CAPE,000P;pl-pl/*/CAPE,000P;tr-tr/*/CAPE,000P;ar-eg/*/CAPE,000P;fil-ph/*/CAPE,000P;ms-my/*/CAPE,000P;vi-vn/*/CAPE,000Q;yue-hant-hk/*/CAPE,000R;zh-hant-tw/*/CAPE,000S;cmn-hans-cn/*/WM8280,1000;cmn-hant-tw/*/WM8280,1001;cs-cz/*/WM8280,1002;da-dk/*/WM8280,100Q;de-*/*/WM8280,100R;en-*/*/WM8280,100S;es-*/*/WM8280,100T;fa-ir/*/WM8280,1007;fi-fi/*/WM8280,1008;fr-*/*/WM8280,100U;hi-in/*/WM8280,000G;hr-hr/*/WM8280,100B;it-it/*/WM8280,100W;ja-jp/*/WM8280,100X;ko-kr/*/WM8280,100Y;nb-no/*/WM8280,100Z;nl-nl/*/WM8280,100a;pt-br/*/WM8280,100H;ro-ro/*/WM8280,100I;ru-ru/*/WM8280,100c;sv-se/*/WM8280,100d;ar-sa/*/WM8280,100L;mr-in/*/WM8280,100L;ta-in/*/WM8280,100L;te-in/*/WM8280,100L;bn-in/*/WM8280,100L;ml-in/*/WM8280,100L;ur-in/*/WM8280,100L;gu-in/*/WM8280,100L;kn-in/*/WM8280,100L;pa-in/*/WM8280,100L;vi-vn/*/WM8280,100N;id-id/*/WM8280,100f;th-th/*/WM8280,100f;pl-pl/*/WM8280,100f;tr-tr/*/WM8280,100f;ar-eg/*/WM8280,100f;fil-ph/*/WM8280,100f;ms-my/*/WM8280,100f;yue-hant-hk/*/WM8280,100h;zh-hant-tw/*/WM8280,100i;de-*/256249082/CM4_MB,200P;en-*/256249082/CM4_MB,200Q;es-*/256249082/CM4_MB,200R;fr-*/256249082/CM4_MB,200S;hi-in/256249082/CM4_MB,200T;it-it/256249082/CM4_MB,200U;it-ch/256249082/CM4_MB,200U;ja-jp/256249082/CM4_MB,200V;ko-kr/256249082/CM4_MB,200W;nb-no/256249082/CM4_MB,200X;nl-be/256249082/CM4_MB,200Y;nl-nl/256249082/CM4_MB,200Y;pt-br/256249082/CM4_MB,200Z;pt-pt/256249082/CM4_MB,200Z;ru-ru/256249082/CM4_MB,200a;sv-se/256249082/CM4_MB,200b;vi-vn/256249082/CM4_MB,200d;yue-hant-hk/256249082/CM4_MB,200e;zh-hk/256249082/CM4_MB,200e;zh-hant-tw/256249082/CM4_MB,200f;zh-tw/256249082/CM4_MB,200f;id-id/256249082/CM4_MB,200M;th-th/256249082/CM4_MB,200M;pl-pl/256249082/CM4_MB,200M;tr-tr/256249082/CM4_MB,200M;ar-eg/256249082/CM4_MB,200M;fil-ph/256249082/CM4_MB,200M;ms-my/256249082/CM4_MB,200M;zh-cn/256249082/CM4_MB,2000;cmn-hans-cn/256249082/CM4_MB,2000;cmn-hant-tw/256249082/CM4_MB,2001;cs-cz/256249082/CM4_MB,2002;da-dk/256249082/CM4_MB,200O;fa-ir/256249082/CM4_MB,2007;fi-fi/256249082/CM4_MB,2008;hr-hr/256249082/CM4_MB,200B;ro-ro/256249082/CM4_MB,200I;ar-sa/256249082/CM4_MB,200L;ar-001/256249082/CM4_MB,200L;mr-in/256249082/CM4_MB,200L;ta-in/256249082/CM4_MB,200L;te-in/256249082/CM4_MB,200L;bn-in/256249082/CM4_MB,200L;ml-in/256249082/CM4_MB,200L;ur-in/256249082/CM4_MB,200L;gu-in/256249082/CM4_MB,200L;kn-in/256249082/CM4_MB,200L;pa-in/256249082/CM4_MB,200L;en-*/282578872/kalimba,300R;fr-*/282578872/kalimba,300T;id-id/282578872/kalimba,300d;th-th/282578872/kalimba,300d;pl-pl/282578872/kalimba,300d;tr-tr/282578872/kalimba,300d;ar-eg/282578872/kalimba,300d;fil-ph/282578872/kalimba,300d;ms-my/282578872/kalimba,300d;es-*/282578872/kalimba,300S;cmn-hant-tw/282578872/kalimba,300Q;cmn-hans-tw/282578872/kalimba,300Q;yue-hk/282578872/kalimba,300Q;yue-hant-hk/282578872/kalimba,300Q;zh-cn/282578872/kalimba,300Q;zh-hans-cn/282578872/kalimba,300Q;zh-hk/282578872/kalimba,300Q;zh-hant-hk/282578872/kalimba,300Q;zh-hant-tw/282578872/kalimba,300Q;zh-tw/282578872/kalimba,300Q;ar-sa/282578872/kalimba,300L;mr-in/282578872/kalimba,300L;ta-in/282578872/kalimba,300L;te-in/282578872/kalimba,300L;bn-in/282578872/kalimba,300L;ml-in/282578872/kalimba,300L;ur-in/282578872/kalimba,300L;gu-in/282578872/kalimba,300L;kn-in/282578872/kalimba,300L;pa-in/282578872/kalimba,300L;en-*/*/AB155x,4000</string>
    <boolean name="flag.11085" value="true" />
    <boolean name="flag.9894" value="true" />
    <string name="flag.12170">com.facebook.orca</string>
    <boolean name="flag.9655" value="true" />
    <boolean name="flag.8560" value="true" />
    <string name="GsaPrefs.Bisto__messaging_parsing_blacklist"></string>
    <boolean name="GsaPrefs.Bisto__enable_bisto_ble_support" value="true" />
    <boolean name="GsaPrefs.AgsaOpaGrowth__enable_nudge_ui" value="true" />
    <boolean name="flag.8667" value="true" />
    <boolean name="flag.10687" value="true" />
    <boolean name="flag.11655" value="true" />
    <boolean name="flag.11776" value="true" />
    <boolean name="flag.4626" value="true" />
    <boolean name="flag.10200" value="true" />
    <boolean name="flag.10441" value="true" />
    <boolean name="flag.12743" value="true" />
    <boolean name="flag.10202" value="true" />
    <boolean name="flag.12861" value="true" />
    <boolean name="flag.10201" value="true" />
    <long name="GsaPrefs.Bisto__hotword_activation_timeout_ms" value="3000" />
    <boolean name="flag.9086" value="true" />
    <boolean name="flag.9082" value="true" />
    <boolean name="flag.9400" value="true" />
    <string name="GSAPrefs.search_gesture_corpus"></string>
    <boolean name="GsaPrefs.Bisto__reconnect_on_gsa_voice_interaction_service_ready" value="true" />
    <boolean name="flag.9881" value="true" />
    <boolean name="flag.9509" value="true" />
    <string name="flag.7324">en-US,en-AU,en-CA,en-GB,en-IE,en-SG,ja-JP</string>
    <string name="flag.7325">Pixel 3,Pixel 3 (Android),Pixel 3 XL,Pixel 4,Pixel 4 (Android),Pixel 4 XL,Pixel 4a,coral,flame,needlefish,sunfish</string>
    <boolean name="flag.12319" value="true" />
    <boolean name="flag.10259" value="true" />
    <boolean name="flag.11346" value="true" />
    <boolean name="flag.11581" value="true" />
    <boolean name="flag.8665" value="true" />
    <boolean name="flag.8422" value="true" />
    <boolean name="flag.9738" value="true" />
    <boolean name="flag.10945" value="true" />
    <boolean name="flag.8888" value="true" />
    <boolean name="flag.12207" value="true" />
    <boolean name="flag.11239" value="true" />
    <string name="flag.11237">docs.google.com,&lt;286159512</string>
    <boolean name="flag.11114" value="true" />
    <long name="flag.12445" value="3" />
    <boolean name="flag.10023" value="true" />
    <boolean name="flag.10026" value="true" />
    <long name="flag.10146" value="3" />
    <long name="flag.12320" value="172800" />
    <boolean name="flag.11232" value="true" />
    <long name="flag.12321" value="604800" />
    <string name="flag.11111"></string>
    <boolean name="flag.8651" value="true" />
    <long name="flag.9861" value="3" />
    <boolean name="flag.8098" value="true" />
    <boolean name="flag.9727" value="true" />
    <long name="flag.9608" value="3" />
    <boolean name="flag.9729" value="true" />
    <boolean name="flag.9607" value="true" />
    <boolean name="flag.9844" value="true" />
    <boolean name="flag.5129" value="true" />
    <long name="flag.12418" value="5184000" />
    <boolean name="flag.9966" value="true" />
    <boolean name="flag.4838" value="true" />
    <boolean name="flag.10116" value="true" />
    <boolean name="flag.10236" value="true" />
    <boolean name="GsaPrefs.Bisto__enable_audio_cache" value="true" />
    <boolean name="flag.10596" value="true" />
    <boolean name="flag.11684" value="true" />
    <boolean name="flag.12411" value="true" />
    <boolean name="flag.10355" value="true" />
    <long name="GSAPrefs.Bisto__service_shutdown_delay_ms" value="600000" />
    <long name="GsaPrefs.Bisto__bitpool_size" value="24" />
    <boolean name="flag.8761" value="true" />
    <string name="GSAPrefs.DARK_MODE_SETTING">-1</string>
    <boolean name="flag.9970" value="true" />
    <boolean name="flag.8089" value="true" />
    <boolean name="flag.10805" value="true" />
    <boolean name="flag.9715" value="true" />
    <boolean name="GsaPrefs.Bisto__enable_personal_response_lockscreen" value="true" />
    <boolean name="flag.10801" value="true" />
    <boolean name="flag.8622" value="true" />
    <boolean name="flag.8987" value="true" />
    <boolean name="flag.8624" value="true" />
    <boolean name="flag.10369" value="true" />
    <boolean name="flag.11699" value="true" />
    <long name="flag.12423" value="0" />
    <boolean name="flag.9719" value="true" />
    <string name="flag.11212">en-US,en-AU,en-CA,en-GB,en-IE,en-SG</string>
    <string name="flag.4391"></string>
    <boolean name="GsaPrefs.Bisto__enable_hotword_helper_speaker_id_nullness_checker" value="true" />
    <boolean name="flag.4396" value="true" />
    <boolean name="flag.8616" value="true" />
    <boolean name="flag.8978" value="true" />
    <boolean name="flag.8615" value="true" />
    <boolean name="flag.8617" value="true" />
    <boolean name="flag.8612" value="true" />
    <boolean name="flag.8611" value="true" />
    <boolean name="flag.8614" value="true" />
    <boolean name="flag.8613" value="true" />
    <boolean name="flag.10853" value="true" />
    <boolean name="flag.11149" value="true" />
    <boolean name="flag.12118" value="true" />
    <long name="flag.10178" value="15" />
    <boolean name="flag.12357" value="true" />
    <boolean name="flag.10057" value="true" />
    <boolean name="flag.10970" value="true" />
    <boolean name="flag.10298" value="true" />
    <boolean name="flag.8619" value="true" />
    <long name="flag.12234" value="2000" />
    <string name="flag.10851"></string>
    <boolean name="flag.11267" value="true" />
    <boolean name="flag.12235" value="true" />
    <string name="flag.10055"></string>
    <boolean name="flag.10296" value="true" />
    <boolean name="flag.12471" value="true" />
    <boolean name="flag.11380" value="true" />
    <boolean name="flag.10292" value="true" />
    <string name="flag.9279"></string>
    <boolean name="flag.9951" value="true" />
    <boolean name="flag.8620" value="true" />
    <boolean name="flag.9277" value="true" />
    <boolean name="flag.9155" value="true" />
    <boolean name="flag.8847" value="true" />
    <boolean name="flag.8843" value="true" />
    <boolean name="flag.10867" value="true" />
    <boolean name="flag.10504" value="true" />
    <boolean name="flag.9931" value="true" />
    <boolean name="flag.9933" value="true" />
    <boolean name="flag.10621" value="true" />
    <boolean name="flag.10866" value="true" />
    <boolean name="flag.12128" value="true" />
    <boolean name="flag.11039" value="true" />
    <boolean name="flag.12008" value="true" />
    <boolean name="flag.8609" value="true" />
    <boolean name="flag.12127" value="true" />
    <boolean name="flag.12488" value="true" />
    <string name="flag.11155">,</string>
    <long name="flag.8294" value="10" />
    <boolean name="flag.11394" value="true" />
    <boolean name="flag.11150" value="true" />
    <boolean name="flag.11272" value="true" />
    <boolean name="flag.8610" value="true" />
    <long name="GsaPrefs.Bisto__tws_role_change_delay" value="2500" />
    <string name="GsaPrefs.Bisto__tts_volume_gain">1.0</string>
    <boolean name="flag.9021" value="true" />
    <string name="flag.11808">ja-JP</string>
    <string name="GsaPrefs.Bisto__enabled_features">4,5,8,9,11,19,21,25,26,27,28,29,31,47,30,40,39,56,67,71,72,49,61,70,75,76,77,78,79,83,84,86</string>
    <boolean name="GEL.GSAPrefs.log_gel_events" value="true" />
    <boolean name="flag.12458" value="true" />
    <long name="flag.12337" value="100" />
    <boolean name="flag.12214" value="true" />
    <boolean name="flag.12457" value="true" />
    <long name="flag.12336" value="0" />
    <boolean name="flag.12334" value="true" />
    <boolean name="flag.12452" value="true" />
    <boolean name="flag.12451" value="true" />
    <boolean name="GSAPrefs.recents_in_drawer" value="true" />
    <string name="flag.8720"></string>
    <boolean name="flag.8841" value="true" />
    <boolean name="flag.5210" value="true" />
    <boolean name="GSAPrefs.search_gesture_used" value="true" />
    <string name="GsaPrefs.Bisto__dsp_hotword_model_location_map">0000,;0001,;0002,;0003,;0004,;0005,;0006,;0007,;0008,;0009,;000A,;000B,;000C,;000D,;000E,;000F,;000G,;000H,;000I,;000J,;000K,;000L,;000M,;000N,;000O,;000P,;000Q,;000R,;000S,;1000,;1001,;1002,;1003,;1004,;1005,;1006,;1007,;1008,;1009,;100A,;100B,;100C,;100D,;100E,;100F,;100G,;100H,;100I,;100J,;100K,;100L,;100N,;100O,;100P,;100Q,;100R,;100S,;100T,;100U,;100V,;100W,;100X,;100Y,;100Z,;100a,;100b,;100c,;100d,;100f,;100g,;100h,;100i,;2000,https://www.gstatic.com/bisto/ota/hotword_model/CM4_MB_256249082/ok/cmn_hans_cn.ota;2001,https://www.gstatic.com/bisto/ota/hotword_model/CM4_MB_256249082/ok/cmn_hant_tw.ota;2002,https://www.gstatic.com/bisto/ota/hotword_model/CM4_MB_256249082/ok/cs_cz.ota;2003,;2004,;2005,;2006,;2007,https://www.gstatic.com/bisto/ota/hotword_model/CM4_MB_256249082/ok/fa_ir.ota;2008,https://www.gstatic.com/bisto/ota/hotword_model/CM4_MB_256249082/ok/fi_fi.ota;2009,;200A,;200B,https://www.gstatic.com/bisto/ota/hotword_model/CM4_MB_256249082/ok/hr_hr.ota;200C,;200D,;200E,;200F,;200G,;200H,;200I,https://www.gstatic.com/bisto/ota/hotword_model/CM4_MB_256249082/ok/ro_ro.ota;200J,;200K,;200L,https://www.gstatic.com/bisto/ota/hotword_model/CM4_MB_256249082/ok/universal.ota;200M,https://www.gstatic.com/bisto/ota/hotword_model/CM4_MB_256249082/universal.ota;200N,;200O,https://www.gstatic.com/bisto/ota/hotword_model/CM4_MB_256249082/da_dk.ota;200P,https://www.gstatic.com/bisto/ota/hotword_model/CM4_MB_256249082/de_de.ota;200Q,https://www.gstatic.com/bisto/ota/hotword_model/CM4_MB_256249082/en_all.ota;200R,https://www.gstatic.com/bisto/ota/hotword_model/CM4_MB_256249082/es_es.ota;200S,https://www.gstatic.com/bisto/ota/hotword_model/CM4_MB_256249082/fr_fr.ota;200T,https://www.gstatic.com/bisto/ota/hotword_model/CM4_MB_256249082/hi_in.ota;200U,https://www.gstatic.com/bisto/ota/hotword_model/CM4_MB_256249082/it_it.ota;200V,https://www.gstatic.com/bisto/ota/hotword_model/CM4_MB_256249082/ja_jp.ota;200W,https://www.gstatic.com/bisto/ota/hotword_model/CM4_MB_256249082/ko_kr.ota;200X,https://www.gstatic.com/bisto/ota/hotword_model/CM4_MB_256249082/nb_no.ota;200Y,https://www.gstatic.com/bisto/ota/hotword_model/CM4_MB_256249082/nl_nl.ota;200Z,https://www.gstatic.com/bisto/ota/hotword_model/CM4_MB_256249082/pt_br.ota;200a,https://www.gstatic.com/bisto/ota/hotword_model/CM4_MB_256249082/ru_ru.ota;200b,https://www.gstatic.com/bisto/ota/hotword_model/CM4_MB_256249082/sv_se.ota;200c,;200d,https://www.gstatic.com/bisto/ota/hotword_model/CM4_MB_256249082/vi_vn.ota;200e,https://www.gstatic.com/bisto/ota/hotword_model/CM4_MB_256249082/yue_hant_hk.ota;200f,https://www.gstatic.com/bisto/ota/hotword_model/CM4_MB_256249082/zh_hant_tw.ota;3000,;3001,;3002,;3003,;3004,;3005,;3006,;3007,;3008,;3009,;300A,;300B,;300C,;300D,;300E,;300F,;300G,;300H,;300I,;300J,;300K,;300L,;300M,;300N,;300O,;300P,;300Q,;300R,;300S,;300T,;300U,;300V,;300W,;300X,;300Y,;300Z,;300a,;300b,;300c,;300d,;300e,;4000,</string>
    <boolean name="flag.9914" value="true" />
    <long name="flag.9913" value="750" />
    <boolean name="flag.9916" value="true" />
    <boolean name="flag.8705" value="true" />
    <long name="flag.9912" value="750" />
    <boolean name="flag.8943" value="true" />
    <boolean name="flag.8822" value="true" />
    <boolean name="GsaPrefs.AgsaNow__enable_restore_on_minus_one" value="true" />
    <boolean name="GSAPrefs.hotword_enabled" value="true" />
    <string name="flag.11256">ElEKAmVuEgkKAggBFQAAAD8SCQoCCAIVMzMzPxIJCgIIBBWamVk/EgkKAggKFZqZmT4SCQoCCAsVzcxMPhIJCgIIDBUAAAA/EgkKAggNFWZmZj8=</string>
    <boolean name="flag.10163" value="true" />
    <boolean name="flag.11253" value="true" />
    <string name="flag.11254">EmcKAmVuEgkKAggBFQAAAD8SCQoCCAIVAAAAPxIJCgIIAxUAAAA/EgkKAggKFQAAQD8SCQoCCAsVAAAAPxIJCgIIDhUAAMBAEgkKAggMFWZmJj8SCQoCCA0VmplZPxIJCgIIEBXNzAw/</string>
    <long name="flag.10161" value="51032000" />
    <long name="flag.10160" value="453039" />
    <boolean name="flag.9246" value="true" />
    <long name="GsaPrefs.Bisto__voice_buffer_duration_ms" value="1200" />
    <boolean name="flag.4474" value="true" />
    <boolean name="flag.9243" value="true" />
    <boolean name="flag.4213" value="true" />
    <boolean name="flag.7848" value="true" />
    <boolean name="flag.11626" value="true" />
    <boolean name="flag.10539" value="true" />
    <string name="flag.10897">en-US,en-AU,en-CA,en-GB,en-IE,en-SG</string>
    <string name="flag.10896">en-US,en-AU,en-CA,en-GB,en-IE,en-SG,ja-JP</string>
    <string name="flag.10899">en-US,en-AU,en-CA,en-GB,en-IE,en-SG</string>
    <boolean name="flag.11865" value="true" />
    <string name="flag.10898">en-US,en-AU,en-CA,en-GB,en-IE,en-SG</string>
    <string name="flag.10893">en-US,en-AU,en-CA,en-GB,en-IE,en-SG</string>
    <string name="flag.10892">en-US,en-AU,en-CA,en-GB,en-IE,en-SG,ja-JP</string>
    <boolean name="flag.12157" value="true" />
    <string name="flag.10895">en-US,en-AU,en-CA,en-GB,en-IE,en-SG,ja-JP</string>
    <string name="flag.10894">en-US,en-AU,en-CA,en-GB,en-IE,en-SG</string>
    <boolean name="flag.8261" value="true" />
    <string name="flag.10891">en-US,en-AU,en-CA,en-GB,en-IE,en-SG,ja-JP</string>
    <string name="flag.10890">en-US,en-AU,en-CA,en-GB,en-IE,en-SG,ja-JP</string>
    <boolean name="flag.11060" value="true" />
    <boolean name="flag.11182" value="true" />
    <boolean name="flag.8267" value="true" />
    <boolean name="flag.11180" value="true" />
    <string name="flag.8384">en-US,en-AU,en-CA,en-GB,en-IE,en-SG</string>
    <string name="flag.1195">0,30</string>
    <boolean name="flag.3113" value="true" />
    <string name="GSAPrefs.hotword_prompt">Ok Google</string>
    <boolean name="flag.5774" value="true" />
    <boolean name="GsaPrefs.AgsaOpa__enable_message_style_parser_for_messages_and_hangouts" value="true" />
    <boolean name="GEL.GSAPrefs.search_widget_in_gel" value="true" />
    <boolean name="flag.9459" value="true" />
    <string name="flag.10428"></string>
    <boolean name="flag.10427" value="true" />
    <boolean name="flag.6985" value="true" />
    <boolean name="flag.10545" value="true" />
    <boolean name="flag.11875" value="true" />
    <boolean name="flag.10546" value="true" />
    <long name="flag.8928" value="-1" />
    <boolean name="flag.11873" value="true" />
    <boolean name="flag.11874" value="true" />
    <string name="flag.12168">com.google.android.apps.nexuslauncher</string>
    <boolean name="flag.11871" value="true" />
    <boolean name="flag.11872" value="true" />
    <boolean name="flag.992" value="true" />
    <string name="flag.11870">CgYIARjd9gIKBggEGMfMAgoaCAIYquABGNjvARigkAIY2e8BGNngBBj3jgUKpAEIAxILV2VhdGhlckNvbGQSB1dlYXRoZXISCldlYXRoZXJIb3QSD1dlYXRoZXJIdW1pZGl0eRIUV2VhdGhlclJhaW5BY2Nlc3NvcnkSC1dlYXRoZXJSYWluEgtXZWF0aGVyU25vdxIMV2VhdGhlclN1bm55EhtXZWF0aGVyVGVtcGVyYXR1cmVGZWVsc0xpa2USEldlYXRoZXJUZW1wZXJhdHVyZQ==</string>
    <string name="GsaPrefs.Bisto__user_group_name">Public</string>
    <boolean name="flag.11074" value="true" />
    <boolean name="flag.9344" value="true" />
    <boolean name="flag.9588" value="true" />
    <boolean name="flag.9342" value="true" />
    <boolean name="flag.11845" value="true" />
    <long name="GsaPrefs.AgsaOpaGrowth__nudge_ui_per_app_display_cap" value="0" />
    <boolean name="flag.11961" value="true" />
    <boolean name="flag.10992" value="true" />
    <boolean name="flag.11962" value="true" />
    <boolean name="flag.10751" value="true" />
    <boolean name="flag.10075" value="true" />
    <boolean name="flag.12495" value="true" />
    <boolean name="flag.9690" value="true" />
    <boolean name="flag.11281" value="true" />
    <boolean name="flag.7258" value="true" />
    <boolean name="flag.10769" value="true" />
    <string name="flag.10526">WeatherCold,Weather,WeatherHot,WeatherHumidity,WeatherRainAccessory,WeatherRain,WeatherSnow,WeatherSunny,WeatherTemperatureFeelsLike,WeatherTemperature,Curated_answer_information</string>
    <string name="flag.10889">en-US,en-AU,en-CA,en-GB,en-IE,en-SG,ja-JP</string>
    <long name="flag.9799" value="3" />
    <boolean name="flag.8105" value="true" />
    <boolean name="flag.5998" value="true" />
    <boolean name="flag.11734" value="true" />
    <long name="flag.4308" value="2" />
    <string name="flag.10888">en-US,en-AU,en-CA,en-GB,en-IE,en-SG</string>
    <boolean name="flag.11975" value="true" />
    <string name="flag.10887">en-US,en-AU,en-CA,en-GB,en-IE,en-SG</string>
    <boolean name="flag.11058" value="true" />
    <long name="GsaPrefs.Bisto__announcement_promotion_timeout_ms" value="180000" />
    <long name="flag.10085" value="0" />
    <string name="flag.11298">com.google.android.apps.docs,&lt;286159512;com.google.android.apps.docs.editors.docs,&lt;286159512;com.google.android.apps.docs.editors.sheets,&lt;286159512;com.google.android.apps.docs.editors.slides,&lt;286159512;com.google.android.calendar,*;com.google.android.googlequicksearchbox,*</string>
    <boolean name="flag.12382" value="true" />
    <long name="flag.11172" value="0" />
    <boolean name="GsaPrefs.AgsaOpa__enable_read_all_group_messages" value="true" />
    <long name="flag.12262" value="0" />
    <boolean name="flag.12381" value="true" />
    <boolean name="flag.8234" value="true" />
    <string name="flag.9201">GetAlarmInfo,CreateAlarm,DisableAlarm,SilenceAlarm,SnoozeAlarm,SendMessage,Permissions</string>
    <long name="GsaPrefs.AgsaOpaGrowth__overapp_suggestions_shown_per_app_display_cap" value="0" />
    <boolean name="flag.5882" value="true" />
    <string name="flag.9560">gmail,assisted_browse</string>
    <boolean name="flag.9684" value="true" />
    <boolean name="flag.9200" value="true" />
    <boolean name="flag.8231" value="true" />
</map>
